Metadata-Version: 2.1
Name: chatlogger-db
Version: 0.1.5
Summary: This is a simple Tree based database to store chats logs for a large language model. to save ollama or any other llm app chat history
Home-page: https://github.com/thefcraft/chatlogger
Author: ThefCraft
Author-email: sisodiyalaksh@gmail.com
License: UNKNOWN
Platform: UNKNOWN
Classifier: Programming Language :: Python :: 3
Classifier: License :: OSI Approved :: MIT License
Classifier: Operating System :: OS Independent
